{
    "id":4,
    "type": "Arme",
    "nom":"arc en bois",
    "description":"Un arc en bois. Moins performant qu'un arc en carbone, il demande plus d'énergie pour le manier.",
    "perte de l'arme en attaquant à distance":false,
    "attaque_type":"attaque unique",
    "effets":{
        "cout energie":{
            "corps à corps":0.5,
            "distance":0.7,
            "magique":null
        },
        "attaque":{
            "corps à corps":[0, 1],
            "distance":[0, 4],
            "magique":null
        }
    }
}